matrix_registration_bot/__init__.py
matrix_registration_bot/bot.py
matrix_registration_bot/config.py
matrix_registration_bot/registration_api.py
tests/__init__.py
tests/test_registration_api.py
venv/bin/activate_this.py
venv/bin/pwiz.py
venv/bin/rst2html.py
venv/bin/rst2html4.py
venv/bin/rst2html5.py
venv/bin/rst2latex.py
venv/bin/rst2man.py
venv/bin/rst2odt.py
venv/bin/rst2odt_prepstyles.py
venv/bin/rst2pseudoxml.py
venv/bin/rst2s5.py
venv/bin/rst2xetex.py
venv/bin/rst2xml.py
venv/bin/rstpep2html.py
matrix_registration_bot-1.2.2.dist-info/LICENSE.TXT
matrix_registration_bot-1.2.2.dist-info/METADATA
matrix_registration_bot-1.2.2.dist-info/WHEEL
matrix_registration_bot-1.2.2.dist-info/entry_points.txt
matrix_registration_bot-1.2.2.dist-info/top_level.txt
matrix_registration_bot-1.2.2.dist-info/RECORD
