Metadata-Version: 2.1
Name: matrix-registration-bot
Version: 1.2.2
Summary: A bot to manage user registration tokens on a matrix server.
License: AGPL-3.0-or-later
Keywords: matrix,registration,bot,user,registration,API
Classifier: Development Status :: 5 - Production/Stable
Classifier: Intended Audience :: System Administrators
Classifier: License :: OSI Approved :: GNU Affero General Public License v3
Classifier: Operating System :: OS Independent
Classifier: Programming Language :: Python :: 3.9
Classifier: Programming Language :: Python :: 3.10
License-File: LICENSE.TXT
Requires-Dist: simplematrixbotlib (<3.0.0,>=2.7.3)
Requires-Dist: pyyaml
Requires-Dist: matrix-nio[e2e]
Requires-Dist: aiohttp[speedups]
